sklearn_model/__init__.py
sklearn_model/export.py
sklearn_model/utils.py
sklearn_model/version.py
sklearn_model-0.0.6.dist-info/LICENSE
sklearn_model-0.0.6.dist-info/METADATA
sklearn_model-0.0.6.dist-info/WHEEL
sklearn_model-0.0.6.dist-info/top_level.txt
sklearn_model-0.0.6.dist-info/RECORD
